sikert/__init__.py
sikert/alienvault.py
sikert/anubis.py
sikert/binaryedge.py
sikert/certspotter.py
sikert/chaos.py
sikert/crtsh.py
sikert/recondev.py
sikert/securitytrails.py
sikert/shodan.py
sikert/sonar.py
sikert/spyse.py
sikert/sublist3r.py
sikert/threatcrowd.py
sikert/threatminer.py
sikert/virustotal.py
sikert-0.0.1.dist-info/LICENSE
sikert-0.0.1.dist-info/METADATA
sikert-0.0.1.dist-info/WHEEL
sikert-0.0.1.dist-info/top_level.txt
sikert-0.0.1.dist-info/RECORD
